d2a/__init__.py
d2a/apps.py
d2a/compat.py
d2a/db.py
d2a/fields.py
d2a/geoalchemy2.py
d2a/missing.py
d2a/original_types.py
d2a/parsers.py
d2a/resolvers.py
d2a/template.py
d2a/utils.py
d2a/management/__init__.py
d2a/management/commands/__init__.py
d2a/management/commands/sqla_codegen.py
d2a-3.0.1.dist-info/LICENSE
d2a-3.0.1.dist-info/METADATA
d2a-3.0.1.dist-info/WHEEL
d2a-3.0.1.dist-info/top_level.txt
d2a-3.0.1.dist-info/RECORD
