Metadata-Version: 2.1
Name: d2a
Version: 3.0.1
Summary: It translates django models into sqlalchemy orm/expression objects.
Home-page: https://github.com/walkframe/d2a
Author: righ
Author-email: righ.m9@gmail.com
License: MIT
Keywords: django,sqlalchemy,alchemy,model,mapping,decralation,table,schema,expression,orm,convert,codegen
Platform: UNKNOWN
Classifier: Intended Audience :: Developers
Classifier: License :: OSI Approved :: MIT License
Classifier: Programming Language :: Python
Classifier: Topic :: Software Development
